{
    "0115": {
        "value": "-2.240429",
        "timestamp": "2025-05-23T13:45:00.000Z"
    },
    "0116": {
        "value": "-2.5192",
        "timestamp": "2025-05-23T13:45:00.000Z"
    },
    "0118": {
        "value": "-2.875492",
        "timestamp": "2025-05-23T13:45:00.000Z"
    },
    "0119": {
        "value": "-2.667029",
        "timestamp": "2025-05-23T13:45:00.000Z"
    },
    "0121": {
        "value": "-3.492364",
        "timestamp": "2025-05-23T13:45:00.000Z"
    },
    "0131": {
        "value": "-3.289572",
        "timestamp": "2025-05-23T13:30:00.000Z"
    },
    "0132": {
        "value": "-3.065483",
        "timestamp": "2025-05-23T13:45:00.000Z"
    },
    "0133": {
        "value": "-3.257522",
        "timestamp": "2025-05-23T13:45:00.000Z"
    },
    "0134": {
        "value": "0.007509836",
        "timestamp": "2025-05-23T13:45:00.000Z"
    },
    "0141": {
        "value": "-2.236583",
        "timestamp": "2025-05-23T13:25:00.000Z"
    },
    "0143": {
        "value": "-2.893262",
        "timestamp": "2025-05-23T13:00:00.000Z"
    },
    "0144": {
        "value": "-3.423278",
        "timestamp": "2025-05-23T13:30:00.000Z"
    },
    "0151": {
        "value": "-6.65035",
        "timestamp": "2025-05-23T13:30:00.000Z"
    },
    "0152": {
        "value": "-5.570267",
        "timestamp": "2025-05-23T13:25:00.000Z"
    },
    "0153": {
        "value": "-3.334875",
        "timestamp": "2025-05-23T13:45:00.000Z"
    },
    "0154": {
        "value": "-2.190661",
        "timestamp": "2025-05-23T13:45:00.000Z"
    },
    "0155": {
        "value": "-1.548461",
        "timestamp": "2025-05-23T13:45:00.000Z"
    },
    "0156": {
        "value": "0.009372448",
        "timestamp": "2025-05-23T13:45:00.000Z"
    },
    "0161": {
        "value": "0.009968368",
        "timestamp": "2025-05-23T13:30:00.000Z"
    },
    "0166": {
        "value": "-1.635084",
        "timestamp": "2025-05-23T13:40:00.000Z"
    },
    "0201": {
        "value": "-1.03871",
        "timestamp": "2025-05-23T13:45:00.000Z"
    },
    "0202": {
        "value": "-2.384453",
        "timestamp": "2025-05-23T13:45:00.000Z"
    },
    "0204": {
        "value": "-1.465913",
        "timestamp": "2025-05-23T13:45:00.000Z"
    },
    "0211": {
        "value": "0.05411081",
        "timestamp": "2025-05-23T13:45:00.000Z"
    },
    "0212": {
        "value": "-2.907403",
        "timestamp": "2025-05-23T13:45:00.000Z"
    },
    "0213": {
        "value": "-1.196299",
        "timestamp": "2025-05-23T13:45:00.000Z"
    },
    "0214": {
        "value": "-0.03885117",
        "timestamp": "2025-05-23T13:45:00.000Z"
    },
    "0221": {
        "value": "-3.698724",
        "timestamp": "2025-05-23T13:40:00.000Z"
    },
    "0222": {
        "value": "-4.623941",
        "timestamp": "2025-05-23T13:45:00.000Z"
    },
    "0231": {
        "value": "-2.676959",
        "timestamp": "2025-05-23T13:45:00.000Z"
    },
    "0241": {
        "value": "-2.539523",
        "timestamp": "2025-05-23T13:45:00.000Z"
    },
    "0242": {
        "value": "-5.183007",
        "timestamp": "2025-05-23T13:45:00.000Z"
    },
    "0243": {
        "value": "-2.795339",
        "timestamp": "2025-05-23T13:45:00.000Z"
    },
    "0244": {
        "value": "-3.89792",
        "timestamp": "2025-05-23T13:45:00.000Z"
    },
    "0245": {
        "value": null,
        "timestamp": "2025-04-16T07:45:00.000Z"
    },
    "0251": {
        "value": "-1.639831",
        "timestamp": "2025-05-23T13:30:00.000Z"
    },
    "0252": {
        "value": "-3.668993",
        "timestamp": "2025-05-23T13:45:00.000Z"
    },
    "0253": {
        "value": "-3.27324",
        "timestamp": "2025-05-23T13:45:00.000Z"
    },
    "0254": {
        "value": "-3.524472",
        "timestamp": "2025-05-23T13:30:00.000Z"
    },
    "0255": {
        "value": "-0.1246782",
        "timestamp": "2025-05-23T13:45:00.000Z"
    },
    "0281": {
        "value": "-1.504833",
        "timestamp": "2025-05-23T13:45:00.000Z"
    },
    "0282": {
        "value": "-1.0207",
        "timestamp": "2025-05-23T13:45:00.000Z"
    },
    "0283": {
        "value": "-2.097799",
        "timestamp": "2025-05-23T13:30:00.000Z"
    },
    "0286": {
        "value": null,
        "timestamp": "2025-05-13T01:00:00.000Z"
    },
    "0287": {
        "value": "-0.5124333",
        "timestamp": "2025-05-23T13:45:00.000Z"
    },
    "0288": {
        "value": null,
        "timestamp": "2025-02-20T10:00:00.000Z"
    },
    "0411": {
        "value": "-0.7881501",
        "timestamp": "2025-05-23T13:45:00.000Z"
    },
    "0412": {
        "value": "-1.355328",
        "timestamp": "2025-05-23T13:45:00.000Z"
    },
    "0431": {
        "value": "-3.145791",
        "timestamp": "2025-05-23T13:45:00.000Z"
    },
    "0501": {
        "value": "-1.284451",
        "timestamp": "2025-05-23T13:25:00.000Z"
    },
    "0502": {
        "value": "-2.437359",
        "timestamp": "2025-05-23T13:45:00.000Z"
    },
    "0506": {
        "value": "0.2394885",
        "timestamp": "2025-05-23T13:30:00.000Z"
    },
    "0521": {
        "value": "0.005596223",
        "timestamp": "2025-05-23T13:30:00.000Z"
    },
    "0531": {
        "value": "-0.94015",
        "timestamp": "2025-05-23T13:45:00.000Z"
    },
    "0541": {
        "value": "-0.7660906",
        "timestamp": "2025-05-23T13:45:00.000Z"
    },
    "0551": {
        "value": "-2.136147",
        "timestamp": "2025-05-23T13:40:00.000Z"
    },
    "0601": {
        "value": "-1.835601",
        "timestamp": "2025-05-23T13:30:00.000Z"
    },
    "0602": {
        "value": "-1.40301",
        "timestamp": "2025-05-23T13:45:00.000Z"
    },
    "0603": {
        "value": "-2.551402",
        "timestamp": "2025-05-23T13:45:00.000Z"
    },
    "0611": {
        "value": "-2.571543",
        "timestamp": "2025-05-23T13:45:00.000Z"
    },
    "0621": {
        "value": "-4.005882",
        "timestamp": "2025-05-23T13:45:00.000Z"
    },
    "0641": {
        "value": "-0.6377766",
        "timestamp": "2025-05-23T13:45:00.000Z"
    }
}