{
    "0115": {
        "value": "359.0538",
        "timestamp": "2025-04-23T17:45:00.000Z"
    },
    "0116": {
        "value": "92.45884",
        "timestamp": "2025-04-23T17:45:00.000Z"
    },
    "0118": {
        "value": "245.1044",
        "timestamp": "2025-04-23T17:30:00.000Z"
    },
    "0119": {
        "value": "236.1795",
        "timestamp": "2025-04-23T17:45:00.000Z"
    },
    "0121": {
        "value": "355.4671",
        "timestamp": "2025-04-23T17:45:00.000Z"
    },
    "0131": {
        "value": "94.77957",
        "timestamp": "2025-04-23T17:45:00.000Z"
    },
    "0132": {
        "value": "95.55497",
        "timestamp": "2025-04-23T17:45:00.000Z"
    },
    "0133": {
        "value": "388.3716",
        "timestamp": "2025-04-23T17:45:00.000Z"
    },
    "0134": {
        "value": "68.87458",
        "timestamp": "2025-04-23T17:45:00.000Z"
    },
    "0141": {
        "value": null,
        "timestamp": "2025-04-23T14:45:00.000Z"
    },
    "0143": {
        "value": "60.14386",
        "timestamp": "2025-04-23T17:30:00.000Z"
    },
    "0144": {
        "value": "77.62128",
        "timestamp": "2025-04-23T17:45:00.000Z"
    },
    "0151": {
        "value": "395.6882",
        "timestamp": "2025-04-23T17:45:00.000Z"
    },
    "0152": {
        "value": "324.5631",
        "timestamp": "2025-04-23T17:45:00.000Z"
    },
    "0153": {
        "value": "401.99",
        "timestamp": "2025-04-23T17:45:00.000Z"
    },
    "0154": {
        "value": "421.3533",
        "timestamp": "2025-04-23T17:45:00.000Z"
    },
    "0155": {
        "value": "247.7125",
        "timestamp": "2025-04-23T17:40:00.000Z"
    },
    "0161": {
        "value": null,
        "timestamp": "2024-06-16T13:15:00.000Z"
    },
    "0166": {
        "value": "337.8021",
        "timestamp": "2025-04-23T17:45:00.000Z"
    },
    "0201": {
        "value": null,
        "timestamp": "2025-04-23T06:30:00.000Z"
    },
    "0202": {
        "value": "489.9159",
        "timestamp": "2025-04-23T17:45:00.000Z"
    },
    "0204": {
        "value": "245.4152",
        "timestamp": "2025-04-23T17:45:00.000Z"
    },
    "0211": {
        "value": "405.5312",
        "timestamp": "2025-04-23T17:45:00.000Z"
    },
    "0212": {
        "value": "257.7748",
        "timestamp": "2025-04-23T17:45:00.000Z"
    },
    "0213": {
        "value": "325.7902",
        "timestamp": "2025-04-23T17:45:00.000Z"
    },
    "0214": {
        "value": "382.2205",
        "timestamp": "2025-04-23T17:45:00.000Z"
    },
    "0221": {
        "value": "345.4067",
        "timestamp": "2025-04-23T17:30:00.000Z"
    },
    "0222": {
        "value": "332.9628",
        "timestamp": "2025-04-23T17:30:00.000Z"
    },
    "0231": {
        "value": "148.4325",
        "timestamp": "2025-04-23T17:45:00.000Z"
    },
    "0241": {
        "value": "349.1944",
        "timestamp": "2025-04-23T17:45:00.000Z"
    },
    "0242": {
        "value": "361.8693",
        "timestamp": "2025-04-23T17:45:00.000Z"
    },
    "0243": {
        "value": "332.8146",
        "timestamp": "2025-04-23T17:30:00.000Z"
    },
    "0244": {
        "value": "329.0777",
        "timestamp": "2025-04-23T17:30:00.000Z"
    },
    "0245": {
        "value": null,
        "timestamp": "2025-03-19T08:30:00.000Z"
    },
    "0251": {
        "value": "412.5329",
        "timestamp": "2025-04-23T17:45:00.000Z"
    },
    "0252": {
        "value": "370.8733",
        "timestamp": "2025-04-23T17:45:00.000Z"
    },
    "0253": {
        "value": "306.9073",
        "timestamp": "2025-04-23T17:30:00.000Z"
    },
    "0254": {
        "value": "327.5777",
        "timestamp": "2025-04-23T17:45:00.000Z"
    },
    "0255": {
        "value": "164.383",
        "timestamp": "2025-04-23T17:45:00.000Z"
    },
    "0281": {
        "value": "62.37466",
        "timestamp": "2025-04-23T17:45:00.000Z"
    },
    "0282": {
        "value": "358.4424",
        "timestamp": "2025-04-23T17:45:00.000Z"
    },
    "0283": {
        "value": "383.5035",
        "timestamp": "2025-04-23T17:45:00.000Z"
    },
    "0286": {
        "value": "352.2643",
        "timestamp": "2025-04-23T17:45:00.000Z"
    },
    "0287": {
        "value": "329.3046",
        "timestamp": "2025-04-23T17:45:00.000Z"
    },
    "0288": {
        "value": null,
        "timestamp": "2025-02-20T10:00:00.000Z"
    },
    "0411": {
        "value": "302.1557",
        "timestamp": "2025-04-23T17:45:00.000Z"
    },
    "0412": {
        "value": "203.61",
        "timestamp": "2025-04-23T17:45:00.000Z"
    },
    "0431": {
        "value": "277.9957",
        "timestamp": "2025-04-23T17:30:00.000Z"
    },
    "0501": {
        "value": "72.25054",
        "timestamp": "2025-04-23T17:35:00.000Z"
    },
    "0502": {
        "value": "106.5666",
        "timestamp": "2025-04-23T17:45:00.000Z"
    },
    "0506": {
        "value": "18.34899",
        "timestamp": "2025-04-23T17:15:00.000Z"
    },
    "0521": {
        "value": "102.4928",
        "timestamp": "2025-04-23T17:45:00.000Z"
    },
    "0531": {
        "value": "403.382",
        "timestamp": "2025-04-23T17:45:00.000Z"
    },
    "0541": {
        "value": "429.8242",
        "timestamp": "2025-04-23T17:45:00.000Z"
    },
    "0551": {
        "value": "300.048",
        "timestamp": "2025-04-23T17:40:00.000Z"
    },
    "0601": {
        "value": "59.46048",
        "timestamp": "2025-04-23T17:45:00.000Z"
    },
    "0602": {
        "value": "92.91895",
        "timestamp": "2025-04-23T17:45:00.000Z"
    },
    "0603": {
        "value": "4.797209",
        "timestamp": "2025-04-23T17:45:00.000Z"
    },
    "0621": {
        "value": "111.5977",
        "timestamp": "2025-04-23T17:45:00.000Z"
    },
    "0641": {
        "value": "278.4388",
        "timestamp": "2025-04-23T17:45:00.000Z"
    }
}