{
    "0115": {
        "value": "-2.805593",
        "timestamp": "2025-03-28T15:30:00.000Z"
    },
    "0116": {
        "value": "-1.871498",
        "timestamp": "2025-03-28T15:30:00.000Z"
    },
    "0118": {
        "value": "-3.226847",
        "timestamp": "2025-03-28T15:30:00.000Z"
    },
    "0119": {
        "value": "-1.803141",
        "timestamp": "2025-03-28T15:45:00.000Z"
    },
    "0121": {
        "value": "-3.490623",
        "timestamp": "2025-03-28T15:45:00.000Z"
    },
    "0131": {
        "value": "-3.361242",
        "timestamp": "2025-03-28T15:45:00.000Z"
    },
    "0132": {
        "value": "-3.067184",
        "timestamp": "2025-03-28T15:45:00.000Z"
    },
    "0133": {
        "value": "-2.693993",
        "timestamp": "2025-03-28T15:45:00.000Z"
    },
    "0134": {
        "value": "-3.716753",
        "timestamp": "2025-03-28T15:45:00.000Z"
    },
    "0141": {
        "value": "-2.851757",
        "timestamp": "2025-03-28T15:15:00.000Z"
    },
    "0143": {
        "value": null,
        "timestamp": "2025-03-27T09:00:00.000Z"
    },
    "0144": {
        "value": "-1.881688",
        "timestamp": "2025-03-28T15:15:00.000Z"
    },
    "0151": {
        "value": "-4.151517",
        "timestamp": "2025-03-28T15:45:00.000Z"
    },
    "0152": {
        "value": "-5.625138",
        "timestamp": "2025-03-28T15:45:00.000Z"
    },
    "0153": {
        "value": "-5.195293",
        "timestamp": "2025-03-28T15:45:00.000Z"
    },
    "0154": {
        "value": "-3.652735",
        "timestamp": "2025-03-28T15:45:00.000Z"
    },
    "0155": {
        "value": "-3.028014",
        "timestamp": "2025-03-28T15:40:00.000Z"
    },
    "0161": {
        "value": null,
        "timestamp": "2024-06-16T13:15:00.000Z"
    },
    "0166": {
        "value": "-2.462055",
        "timestamp": "2025-03-28T15:45:00.000Z"
    },
    "0201": {
        "value": "-3.546393",
        "timestamp": "2025-03-28T15:45:00.000Z"
    },
    "0202": {
        "value": "-2.165278",
        "timestamp": "2025-03-28T15:45:00.000Z"
    },
    "0204": {
        "value": "-2.486265",
        "timestamp": "2025-03-28T15:45:00.000Z"
    },
    "0211": {
        "value": "-4.299881",
        "timestamp": "2025-03-28T15:45:00.000Z"
    },
    "0212": {
        "value": "-2.283184",
        "timestamp": "2025-03-28T15:45:00.000Z"
    },
    "0213": {
        "value": "-2.034122",
        "timestamp": "2025-03-28T15:45:00.000Z"
    },
    "0214": {
        "value": "-1.897297",
        "timestamp": "2025-03-28T15:45:00.000Z"
    },
    "0221": {
        "value": "-3.893391",
        "timestamp": "2025-03-28T15:40:00.000Z"
    },
    "0222": {
        "value": "-3.324837",
        "timestamp": "2025-03-28T15:45:00.000Z"
    },
    "0231": {
        "value": "-4.747098",
        "timestamp": "2025-03-28T15:45:00.000Z"
    },
    "0241": {
        "value": "-2.744581",
        "timestamp": "2025-03-28T15:45:00.000Z"
    },
    "0242": {
        "value": "-3.267625",
        "timestamp": "2025-03-28T15:45:00.000Z"
    },
    "0243": {
        "value": "-3.825164",
        "timestamp": "2025-03-28T15:45:00.000Z"
    },
    "0244": {
        "value": "-2.309424",
        "timestamp": "2025-03-28T15:40:00.000Z"
    },
    "0245": {
        "value": null,
        "timestamp": "2025-03-17T12:15:00.000Z"
    },
    "0251": {
        "value": "-3.143527",
        "timestamp": "2025-03-28T15:45:00.000Z"
    },
    "0252": {
        "value": "-3.689271",
        "timestamp": "2025-03-28T15:45:00.000Z"
    },
    "0253": {
        "value": "-2.864139",
        "timestamp": "2025-03-28T15:45:00.000Z"
    },
    "0254": {
        "value": "-2.235611",
        "timestamp": "2025-03-28T15:45:00.000Z"
    },
    "0255": {
        "value": "-2.104116",
        "timestamp": "2025-03-28T15:45:00.000Z"
    },
    "0281": {
        "value": "-2.155167",
        "timestamp": "2025-03-28T15:45:00.000Z"
    },
    "0282": {
        "value": "-0.5378",
        "timestamp": "2025-03-28T15:45:00.000Z"
    },
    "0283": {
        "value": "-4.244518",
        "timestamp": "2025-03-28T15:45:00.000Z"
    },
    "0286": {
        "value": "-3.93536",
        "timestamp": "2025-03-28T15:45:00.000Z"
    },
    "0287": {
        "value": "-0.6887333",
        "timestamp": "2025-03-28T15:45:00.000Z"
    },
    "0288": {
        "value": null,
        "timestamp": "2025-02-20T10:00:00.000Z"
    },
    "0411": {
        "value": "-2.92239",
        "timestamp": "2025-03-28T15:45:00.000Z"
    },
    "0412": {
        "value": "-1.53614",
        "timestamp": "2025-03-28T15:45:00.000Z"
    },
    "0431": {
        "value": "0.3354317",
        "timestamp": "2025-03-28T15:45:00.000Z"
    },
    "0501": {
        "value": "-1.2185",
        "timestamp": "2025-03-28T15:25:00.000Z"
    },
    "0502": {
        "value": "-2.191648",
        "timestamp": "2025-03-28T15:45:00.000Z"
    },
    "0506": {
        "value": "-4.358155",
        "timestamp": "2025-03-28T15:45:00.000Z"
    },
    "0521": {
        "value": "-4.057441",
        "timestamp": "2025-03-28T15:45:00.000Z"
    },
    "0531": {
        "value": "-1.209672",
        "timestamp": "2025-03-28T15:45:00.000Z"
    },
    "0541": {
        "value": "-0.5838356",
        "timestamp": "2025-03-28T15:45:00.000Z"
    },
    "0551": {
        "value": "-2.878482",
        "timestamp": "2025-03-28T15:40:00.000Z"
    },
    "0601": {
        "value": "-2.071435",
        "timestamp": "2025-03-28T15:45:00.000Z"
    },
    "0602": {
        "value": "-1.787177",
        "timestamp": "2025-03-28T15:45:00.000Z"
    },
    "0603": {
        "value": "-2.519417",
        "timestamp": "2025-03-28T15:45:00.000Z"
    },
    "0621": {
        "value": "-2.015275",
        "timestamp": "2025-03-28T15:45:00.000Z"
    },
    "0641": {
        "value": "-3.326358",
        "timestamp": "2025-03-28T15:45:00.000Z"
    }
}