{
    "0115": {
        "value": "20.25279",
        "timestamp": "2025-04-19T01:30:00.000Z"
    },
    "0116": {
        "value": "20.75258",
        "timestamp": "2025-04-19T01:00:00.000Z"
    },
    "0118": {
        "value": "30.16576",
        "timestamp": "2025-04-19T01:30:00.000Z"
    },
    "0119": {
        "value": "18.63467",
        "timestamp": "2025-04-19T01:30:00.000Z"
    },
    "0121": {
        "value": "36.2251",
        "timestamp": "2025-04-19T01:15:00.000Z"
    },
    "0131": {
        "value": "30.70426",
        "timestamp": "2025-04-19T01:30:00.000Z"
    },
    "0132": {
        "value": "34.89526",
        "timestamp": "2025-04-19T01:30:00.000Z"
    },
    "0133": {
        "value": "26.32478",
        "timestamp": "2025-04-19T01:00:00.000Z"
    },
    "0134": {
        "value": "18.14238",
        "timestamp": "2025-04-19T01:30:00.000Z"
    },
    "0141": {
        "value": "18.77112",
        "timestamp": "2025-04-19T01:15:00.000Z"
    },
    "0143": {
        "value": null,
        "timestamp": "2025-04-18T15:00:00.000Z"
    },
    "0144": {
        "value": "20.18896",
        "timestamp": "2025-04-19T01:30:00.000Z"
    },
    "0151": {
        "value": "11.31396",
        "timestamp": "2025-04-19T01:30:00.000Z"
    },
    "0152": {
        "value": "13.19618",
        "timestamp": "2025-04-19T01:30:00.000Z"
    },
    "0153": {
        "value": "12.00028",
        "timestamp": "2025-04-19T01:30:00.000Z"
    },
    "0154": {
        "value": "13.87495",
        "timestamp": "2025-04-19T01:15:00.000Z"
    },
    "0155": {
        "value": "25.29331",
        "timestamp": "2025-04-19T01:10:00.000Z"
    },
    "0161": {
        "value": null,
        "timestamp": "2024-06-16T13:15:00.000Z"
    },
    "0165": {
        "value": null,
        "timestamp": "2024-05-16T16:30:00.000Z"
    },
    "0166": {
        "value": "26.51372",
        "timestamp": "2025-04-19T01:30:00.000Z"
    },
    "0201": {
        "value": "15.97201",
        "timestamp": "2025-04-19T01:30:00.000Z"
    },
    "0202": {
        "value": "26.29627",
        "timestamp": "2025-04-19T01:30:00.000Z"
    },
    "0204": {
        "value": "26.85813",
        "timestamp": "2025-04-19T01:15:00.000Z"
    },
    "0211": {
        "value": "13.40359",
        "timestamp": "2025-04-19T01:30:00.000Z"
    },
    "0212": {
        "value": "24.2823",
        "timestamp": "2025-04-19T01:30:00.000Z"
    },
    "0213": {
        "value": "22.10459",
        "timestamp": "2025-04-19T01:30:00.000Z"
    },
    "0214": {
        "value": "16.58984",
        "timestamp": "2025-04-19T01:30:00.000Z"
    },
    "0221": {
        "value": "16.02372",
        "timestamp": "2025-04-19T01:25:00.000Z"
    },
    "0222": {
        "value": "14.55942",
        "timestamp": "2025-04-19T01:30:00.000Z"
    },
    "0231": {
        "value": "19.09467",
        "timestamp": "2025-04-19T01:30:00.000Z"
    },
    "0241": {
        "value": "29.70057",
        "timestamp": "2025-04-19T01:30:00.000Z"
    },
    "0242": {
        "value": "17.54548",
        "timestamp": "2025-04-19T01:30:00.000Z"
    },
    "0244": {
        "value": "18.40635",
        "timestamp": "2025-04-19T01:30:00.000Z"
    },
    "0245": {
        "value": null,
        "timestamp": "2025-03-19T08:30:00.000Z"
    },
    "0251": {
        "value": "15.99451",
        "timestamp": "2025-04-19T01:30:00.000Z"
    },
    "0252": {
        "value": "25.22068",
        "timestamp": "2025-04-19T01:30:00.000Z"
    },
    "0253": {
        "value": "21.11703",
        "timestamp": "2025-04-19T01:30:00.000Z"
    },
    "0254": {
        "value": "36.22253",
        "timestamp": "2025-04-19T01:30:00.000Z"
    },
    "0255": {
        "value": "16.11441",
        "timestamp": "2025-04-19T01:30:00.000Z"
    },
    "0282": {
        "value": "25.33699",
        "timestamp": "2025-04-19T01:30:00.000Z"
    },
    "0283": {
        "value": "16.57576",
        "timestamp": "2025-04-19T01:30:00.000Z"
    },
    "0288": {
        "value": null,
        "timestamp": "2025-02-20T10:00:00.000Z"
    },
    "0411": {
        "value": "20.55228",
        "timestamp": "2025-04-19T01:30:00.000Z"
    },
    "0412": {
        "value": "22.179",
        "timestamp": "2025-04-19T01:30:00.000Z"
    },
    "0431": {
        "value": null,
        "timestamp": "2025-04-12T17:00:00.000Z"
    },
    "0501": {
        "value": "25.97466",
        "timestamp": "2025-04-19T00:55:00.000Z"
    },
    "0502": {
        "value": "25.97917",
        "timestamp": "2025-04-19T01:30:00.000Z"
    },
    "0506": {
        "value": "20.0716",
        "timestamp": "2025-04-19T01:30:00.000Z"
    },
    "0521": {
        "value": "15.94254",
        "timestamp": "2025-04-19T01:30:00.000Z"
    },
    "0531": {
        "value": "26.78442",
        "timestamp": "2025-04-19T01:30:00.000Z"
    },
    "0541": {
        "value": "23.63572",
        "timestamp": "2025-04-19T01:15:00.000Z"
    },
    "0551": {
        "value": "27.45835",
        "timestamp": "2025-04-19T01:25:00.000Z"
    },
    "0601": {
        "value": "24.22704",
        "timestamp": "2025-04-19T01:30:00.000Z"
    },
    "0602": {
        "value": "27.11342",
        "timestamp": "2025-04-19T01:30:00.000Z"
    },
    "0603": {
        "value": "22.5983",
        "timestamp": "2025-04-19T01:30:00.000Z"
    },
    "0621": {
        "value": "27.68329",
        "timestamp": "2025-04-19T01:30:00.000Z"
    },
    "0641": {
        "value": "22.47633",
        "timestamp": "2025-04-19T01:30:00.000Z"
    }
}