{
    "0115": {
        "value": "20.29666",
        "timestamp": "2025-03-20T04:45:00.000Z"
    },
    "0116": {
        "value": "19.96056",
        "timestamp": "2025-03-20T04:45:00.000Z"
    },
    "0118": {
        "value": "27.12234",
        "timestamp": "2025-03-20T04:45:00.000Z"
    },
    "0119": {
        "value": "19.5725",
        "timestamp": "2025-03-20T04:45:00.000Z"
    },
    "0121": {
        "value": "32.35199",
        "timestamp": "2025-03-20T04:45:00.000Z"
    },
    "0131": {
        "value": "28.65368",
        "timestamp": "2025-03-20T04:45:00.000Z"
    },
    "0132": {
        "value": "31.67475",
        "timestamp": "2025-03-20T04:45:00.000Z"
    },
    "0133": {
        "value": "24.31561",
        "timestamp": "2025-03-20T04:45:00.000Z"
    },
    "0134": {
        "value": "16.77916",
        "timestamp": "2025-03-20T04:45:00.000Z"
    },
    "0141": {
        "value": "18.83331",
        "timestamp": "2025-03-20T04:45:00.000Z"
    },
    "0143": {
        "value": "14.67",
        "timestamp": "2025-03-20T04:45:00.000Z"
    },
    "0144": {
        "value": "20.95162",
        "timestamp": "2025-03-20T04:30:00.000Z"
    },
    "0151": {
        "value": "14.78931",
        "timestamp": "2025-03-20T04:45:00.000Z"
    },
    "0152": {
        "value": "13.84542",
        "timestamp": "2025-03-20T04:45:00.000Z"
    },
    "0153": {
        "value": "10.11539",
        "timestamp": "2025-03-20T04:45:00.000Z"
    },
    "0154": {
        "value": "13.80331",
        "timestamp": "2025-03-20T04:45:00.000Z"
    },
    "0155": {
        "value": "24.41165",
        "timestamp": "2025-03-20T04:40:00.000Z"
    },
    "0161": {
        "value": null,
        "timestamp": "2024-06-16T13:15:00.000Z"
    },
    "0165": {
        "value": null,
        "timestamp": "2024-05-16T16:30:00.000Z"
    },
    "0166": {
        "value": "25.34741",
        "timestamp": "2025-03-20T04:45:00.000Z"
    },
    "0201": {
        "value": "15.46232",
        "timestamp": "2025-03-20T04:45:00.000Z"
    },
    "0202": {
        "value": "24.07799",
        "timestamp": "2025-03-20T04:45:00.000Z"
    },
    "0204": {
        "value": "25.33795",
        "timestamp": "2025-03-20T04:45:00.000Z"
    },
    "0211": {
        "value": "12.64104",
        "timestamp": "2025-03-20T04:45:00.000Z"
    },
    "0212": {
        "value": "23.15059",
        "timestamp": "2025-03-20T04:45:00.000Z"
    },
    "0213": {
        "value": "21.46528",
        "timestamp": "2025-03-20T04:45:00.000Z"
    },
    "0214": {
        "value": "15.97681",
        "timestamp": "2025-03-20T04:45:00.000Z"
    },
    "0221": {
        "value": "14.99628",
        "timestamp": "2025-03-20T04:40:00.000Z"
    },
    "0222": {
        "value": "13.72838",
        "timestamp": "2025-03-20T04:45:00.000Z"
    },
    "0231": {
        "value": "18.90932",
        "timestamp": "2025-03-20T04:45:00.000Z"
    },
    "0241": {
        "value": "22.75618",
        "timestamp": "2025-03-20T04:45:00.000Z"
    },
    "0242": {
        "value": "17.05872",
        "timestamp": "2025-03-20T04:45:00.000Z"
    },
    "0244": {
        "value": "16.67149",
        "timestamp": "2025-03-20T04:40:00.000Z"
    },
    "0245": {
        "value": null,
        "timestamp": "2025-03-17T11:30:00.000Z"
    },
    "0251": {
        "value": null,
        "timestamp": "2025-03-20T00:30:00.000Z"
    },
    "0252": {
        "value": "18.90332",
        "timestamp": "2025-03-20T04:45:00.000Z"
    },
    "0253": {
        "value": "20.34073",
        "timestamp": "2025-03-20T04:45:00.000Z"
    },
    "0254": {
        "value": "31.37329",
        "timestamp": "2025-03-20T04:45:00.000Z"
    },
    "0255": {
        "value": "15.7513",
        "timestamp": "2025-03-20T04:45:00.000Z"
    },
    "0282": {
        "value": "22.03338",
        "timestamp": "2025-03-20T04:45:00.000Z"
    },
    "0283": {
        "value": "16.11954",
        "timestamp": "2025-03-20T04:45:00.000Z"
    },
    "0288": {
        "value": null,
        "timestamp": "2025-02-20T10:00:00.000Z"
    },
    "0411": {
        "value": "22.85934",
        "timestamp": "2025-03-20T04:45:00.000Z"
    },
    "0412": {
        "value": "21.22666",
        "timestamp": "2025-03-20T04:45:00.000Z"
    },
    "0431": {
        "value": "27.24549",
        "timestamp": "2025-03-20T04:45:00.000Z"
    },
    "0501": {
        "value": "25.00681",
        "timestamp": "2025-03-20T04:25:00.000Z"
    },
    "0502": {
        "value": "24.87147",
        "timestamp": "2025-03-20T04:45:00.000Z"
    },
    "0506": {
        "value": "19.87175",
        "timestamp": "2025-03-20T04:45:00.000Z"
    },
    "0521": {
        "value": "16.26231",
        "timestamp": "2025-03-20T04:45:00.000Z"
    },
    "0531": {
        "value": "26.62924",
        "timestamp": "2025-03-20T04:45:00.000Z"
    },
    "0541": {
        "value": "24.17449",
        "timestamp": "2025-03-20T04:45:00.000Z"
    },
    "0551": {
        "value": "25.69862",
        "timestamp": "2025-03-20T04:40:00.000Z"
    },
    "0601": {
        "value": "24.98984",
        "timestamp": "2025-03-20T04:45:00.000Z"
    },
    "0602": {
        "value": "24.30079",
        "timestamp": "2025-03-20T04:45:00.000Z"
    },
    "0603": {
        "value": "22.63695",
        "timestamp": "2025-03-20T04:45:00.000Z"
    },
    "0621": {
        "value": "25.41084",
        "timestamp": "2025-03-20T04:45:00.000Z"
    },
    "0641": {
        "value": "22.84617",
        "timestamp": "2025-03-20T04:45:00.000Z"
    }
}