{
    "0115": {
        "value": "18.00524",
        "timestamp": "2025-03-31T17:00:00.000Z"
    },
    "0116": {
        "value": "18.54733",
        "timestamp": "2025-03-31T17:00:00.000Z"
    },
    "0118": {
        "value": "23.84055",
        "timestamp": "2025-03-31T17:00:00.000Z"
    },
    "0119": {
        "value": "16.41224",
        "timestamp": "2025-03-31T17:00:00.000Z"
    },
    "0121": {
        "value": "29.48097",
        "timestamp": "2025-03-31T17:00:00.000Z"
    },
    "0131": {
        "value": "25.03829",
        "timestamp": "2025-03-31T17:00:00.000Z"
    },
    "0132": {
        "value": "29.60869",
        "timestamp": "2025-03-31T17:00:00.000Z"
    },
    "0133": {
        "value": "24.12576",
        "timestamp": "2025-03-31T17:00:00.000Z"
    },
    "0134": {
        "value": "15.7964",
        "timestamp": "2025-03-31T17:00:00.000Z"
    },
    "0141": {
        "value": "15.80747",
        "timestamp": "2025-03-31T17:00:00.000Z"
    },
    "0143": {
        "value": "12.97",
        "timestamp": "2025-03-31T17:00:00.000Z"
    },
    "0144": {
        "value": "18.97754",
        "timestamp": "2025-03-31T17:00:00.000Z"
    },
    "0151": {
        "value": "7.832109",
        "timestamp": "2025-03-31T17:00:00.000Z"
    },
    "0152": {
        "value": "12.6829",
        "timestamp": "2025-03-31T17:00:00.000Z"
    },
    "0153": {
        "value": "8.847336",
        "timestamp": "2025-03-31T17:00:00.000Z"
    },
    "0154": {
        "value": "8.147131",
        "timestamp": "2025-03-31T17:00:00.000Z"
    },
    "0155": {
        "value": "23.42504",
        "timestamp": "2025-03-31T16:55:00.000Z"
    },
    "0161": {
        "value": null,
        "timestamp": "2024-06-16T13:15:00.000Z"
    },
    "0165": {
        "value": null,
        "timestamp": "2024-05-16T16:30:00.000Z"
    },
    "0166": {
        "value": "25.62805",
        "timestamp": "2025-03-31T17:00:00.000Z"
    },
    "0201": {
        "value": "15.30389",
        "timestamp": "2025-03-31T17:00:00.000Z"
    },
    "0202": {
        "value": "22.15424",
        "timestamp": "2025-03-31T17:00:00.000Z"
    },
    "0204": {
        "value": "24.73015",
        "timestamp": "2025-03-31T17:00:00.000Z"
    },
    "0211": {
        "value": "10.6467",
        "timestamp": "2025-03-31T16:45:00.000Z"
    },
    "0212": {
        "value": "22.10469",
        "timestamp": "2025-03-31T17:00:00.000Z"
    },
    "0213": {
        "value": "20.25938",
        "timestamp": "2025-03-31T17:00:00.000Z"
    },
    "0214": {
        "value": "12.9601",
        "timestamp": "2025-03-31T17:00:00.000Z"
    },
    "0221": {
        "value": "12.02704",
        "timestamp": "2025-03-31T17:00:00.000Z"
    },
    "0222": {
        "value": "11.83848",
        "timestamp": "2025-03-31T17:00:00.000Z"
    },
    "0231": {
        "value": "17.96936",
        "timestamp": "2025-03-31T17:00:00.000Z"
    },
    "0241": {
        "value": "19.24648",
        "timestamp": "2025-03-31T17:00:00.000Z"
    },
    "0242": {
        "value": "16.39378",
        "timestamp": "2025-03-31T17:00:00.000Z"
    },
    "0244": {
        "value": "12.82849",
        "timestamp": "2025-03-31T17:00:00.000Z"
    },
    "0245": {
        "value": null,
        "timestamp": "2025-03-17T12:15:00.000Z"
    },
    "0251": {
        "value": "14.84289",
        "timestamp": "2025-03-31T17:00:00.000Z"
    },
    "0252": {
        "value": "20.32744",
        "timestamp": "2025-03-31T17:00:00.000Z"
    },
    "0253": {
        "value": "20.72788",
        "timestamp": "2025-03-31T17:00:00.000Z"
    },
    "0254": {
        "value": "28.75858",
        "timestamp": "2025-03-31T17:00:00.000Z"
    },
    "0255": {
        "value": "15.31293",
        "timestamp": "2025-03-31T17:00:00.000Z"
    },
    "0282": {
        "value": "20.36013",
        "timestamp": "2025-03-31T17:00:00.000Z"
    },
    "0283": {
        "value": "14.79111",
        "timestamp": "2025-03-31T17:00:00.000Z"
    },
    "0288": {
        "value": null,
        "timestamp": "2025-02-20T10:00:00.000Z"
    },
    "0411": {
        "value": "24.13158",
        "timestamp": "2025-03-31T17:00:00.000Z"
    },
    "0412": {
        "value": "21.79405",
        "timestamp": "2025-03-31T17:00:00.000Z"
    },
    "0431": {
        "value": "26.73195",
        "timestamp": "2025-03-31T17:00:00.000Z"
    },
    "0501": {
        "value": "22.49193",
        "timestamp": "2025-03-31T16:55:00.000Z"
    },
    "0502": {
        "value": "23.05702",
        "timestamp": "2025-03-31T17:00:00.000Z"
    },
    "0506": {
        "value": "19.54838",
        "timestamp": "2025-03-31T17:00:00.000Z"
    },
    "0521": {
        "value": "15.2998",
        "timestamp": "2025-03-31T16:45:00.000Z"
    },
    "0531": {
        "value": "27.41634",
        "timestamp": "2025-03-31T17:00:00.000Z"
    },
    "0541": {
        "value": "23.91694",
        "timestamp": "2025-03-31T17:00:00.000Z"
    },
    "0551": {
        "value": "24.61747",
        "timestamp": "2025-03-31T16:55:00.000Z"
    },
    "0601": {
        "value": "23.49976",
        "timestamp": "2025-03-31T17:00:00.000Z"
    },
    "0602": {
        "value": "23.93874",
        "timestamp": "2025-03-31T17:00:00.000Z"
    },
    "0603": {
        "value": "22.08366",
        "timestamp": "2025-03-31T17:00:00.000Z"
    },
    "0621": {
        "value": "25.60096",
        "timestamp": "2025-03-31T17:00:00.000Z"
    },
    "0641": {
        "value": "21.69009",
        "timestamp": "2025-03-31T17:00:00.000Z"
    }
}