{
    "0115": {
        "value": "21.06965",
        "timestamp": "2025-05-03T20:00:00.000Z"
    },
    "0116": {
        "value": "20.23989",
        "timestamp": "2025-05-03T20:00:00.000Z"
    },
    "0118": {
        "value": "27.56496",
        "timestamp": "2025-05-03T20:00:00.000Z"
    },
    "0119": {
        "value": "18.50444",
        "timestamp": "2025-05-03T19:45:00.000Z"
    },
    "0121": {
        "value": "33.05088",
        "timestamp": "2025-05-03T20:00:00.000Z"
    },
    "0131": {
        "value": "31.63287",
        "timestamp": "2025-05-03T20:00:00.000Z"
    },
    "0132": {
        "value": "31.87819",
        "timestamp": "2025-05-03T20:00:00.000Z"
    },
    "0133": {
        "value": "29.18299",
        "timestamp": "2025-05-03T19:45:00.000Z"
    },
    "0134": {
        "value": "17.52773",
        "timestamp": "2025-05-03T20:00:00.000Z"
    },
    "0141": {
        "value": "16.22544",
        "timestamp": "2025-05-03T19:30:00.000Z"
    },
    "0143": {
        "value": "13.48",
        "timestamp": "2025-05-03T19:45:00.000Z"
    },
    "0144": {
        "value": "19.3783",
        "timestamp": "2025-05-03T19:55:00.000Z"
    },
    "0151": {
        "value": "11.41186",
        "timestamp": "2025-05-03T20:00:00.000Z"
    },
    "0152": {
        "value": "10.19877",
        "timestamp": "2025-05-03T19:55:00.000Z"
    },
    "0153": {
        "value": "12.11217",
        "timestamp": "2025-05-03T20:00:00.000Z"
    },
    "0154": {
        "value": "18.86552",
        "timestamp": "2025-05-03T20:00:00.000Z"
    },
    "0155": {
        "value": "25.54423",
        "timestamp": "2025-05-03T19:55:00.000Z"
    },
    "0161": {
        "value": "9.993298",
        "timestamp": "2025-05-03T19:45:00.000Z"
    },
    "0165": {
        "value": null,
        "timestamp": "2024-05-16T16:30:00.000Z"
    },
    "0166": {
        "value": "26.01067",
        "timestamp": "2025-05-03T19:25:00.000Z"
    },
    "0201": {
        "value": "15.54165",
        "timestamp": "2025-05-03T20:00:00.000Z"
    },
    "0202": {
        "value": "25.33601",
        "timestamp": "2025-05-03T20:00:00.000Z"
    },
    "0204": {
        "value": "25.46159",
        "timestamp": "2025-05-03T19:45:00.000Z"
    },
    "0211": {
        "value": "12.23159",
        "timestamp": "2025-05-03T20:00:00.000Z"
    },
    "0212": {
        "value": "23.82584",
        "timestamp": "2025-05-03T20:00:00.000Z"
    },
    "0213": {
        "value": "21.55662",
        "timestamp": "2025-05-03T20:00:00.000Z"
    },
    "0214": {
        "value": "14.75038",
        "timestamp": "2025-05-03T19:40:00.000Z"
    },
    "0221": {
        "value": "15.40635",
        "timestamp": "2025-05-03T20:10:00.000Z"
    },
    "0222": {
        "value": "14.87951",
        "timestamp": "2025-05-03T20:00:00.000Z"
    },
    "0231": {
        "value": "17.75926",
        "timestamp": "2025-05-03T20:15:00.000Z"
    },
    "0241": {
        "value": "22.28512",
        "timestamp": "2025-05-03T20:00:00.000Z"
    },
    "0242": {
        "value": "17.20331",
        "timestamp": "2025-05-03T20:00:00.000Z"
    },
    "0244": {
        "value": "16.31155",
        "timestamp": "2025-05-03T20:00:00.000Z"
    },
    "0245": {
        "value": null,
        "timestamp": "2025-04-06T21:15:00.000Z"
    },
    "0251": {
        "value": "15.76495",
        "timestamp": "2025-05-03T20:00:00.000Z"
    },
    "0252": {
        "value": "21.15692",
        "timestamp": "2025-05-03T20:00:00.000Z"
    },
    "0253": {
        "value": "20.369",
        "timestamp": "2025-05-03T20:00:00.000Z"
    },
    "0254": {
        "value": "30.7435",
        "timestamp": "2025-05-03T20:15:00.000Z"
    },
    "0255": {
        "value": "16.14415",
        "timestamp": "2025-05-03T20:00:00.000Z"
    },
    "0282": {
        "value": "23.78146",
        "timestamp": "2025-05-03T20:15:00.000Z"
    },
    "0283": {
        "value": "15.39759",
        "timestamp": "2025-05-03T20:15:00.000Z"
    },
    "0288": {
        "value": null,
        "timestamp": "2025-02-20T10:00:00.000Z"
    },
    "0411": {
        "value": "25.76908",
        "timestamp": "2025-05-03T20:15:00.000Z"
    },
    "0412": {
        "value": "22.74724",
        "timestamp": "2025-05-03T20:15:00.000Z"
    },
    "0431": {
        "value": "29.33077",
        "timestamp": "2025-05-03T20:15:00.000Z"
    },
    "0501": {
        "value": "24.90648",
        "timestamp": "2025-05-03T19:45:00.000Z"
    },
    "0502": {
        "value": "24.38518",
        "timestamp": "2025-05-03T20:15:00.000Z"
    },
    "0506": {
        "value": "20.01788",
        "timestamp": "2025-05-03T20:00:00.000Z"
    },
    "0521": {
        "value": "16.2211",
        "timestamp": "2025-05-03T20:15:00.000Z"
    },
    "0531": {
        "value": "26.76244",
        "timestamp": "2025-05-03T20:15:00.000Z"
    },
    "0541": {
        "value": "-7.473911E+07",
        "timestamp": "2025-05-03T20:15:00.000Z"
    },
    "0551": {
        "value": "26.95138",
        "timestamp": "2025-05-03T20:10:00.000Z"
    },
    "0601": {
        "value": "24.60914",
        "timestamp": "2025-05-03T20:15:00.000Z"
    },
    "0602": {
        "value": "25.49491",
        "timestamp": "2025-05-03T20:15:00.000Z"
    },
    "0603": {
        "value": "23.06259",
        "timestamp": "2025-05-03T20:15:00.000Z"
    },
    "0611": {
        "value": "26.31486",
        "timestamp": "2025-05-03T20:15:00.000Z"
    },
    "0621": {
        "value": "26.12723",
        "timestamp": "2025-05-03T20:00:00.000Z"
    },
    "0641": {
        "value": "23.01706",
        "timestamp": "2025-05-03T20:15:00.000Z"
    }
}