{
    "0115": {
        "value": "18.71853",
        "timestamp": "2025-03-26T13:45:00.000Z"
    },
    "0116": {
        "value": "18.48458",
        "timestamp": "2025-03-26T13:45:00.000Z"
    },
    "0118": {
        "value": "24.99712",
        "timestamp": "2025-03-26T13:45:00.000Z"
    },
    "0119": {
        "value": "16.75972",
        "timestamp": "2025-03-26T13:45:00.000Z"
    },
    "0121": {
        "value": "29.33754",
        "timestamp": "2025-03-26T13:45:00.000Z"
    },
    "0131": {
        "value": "27.1681",
        "timestamp": "2025-03-26T13:45:00.000Z"
    },
    "0132": {
        "value": "30.37349",
        "timestamp": "2025-03-26T13:45:00.000Z"
    },
    "0133": {
        "value": "24.04796",
        "timestamp": "2025-03-26T13:45:00.000Z"
    },
    "0134": {
        "value": "15.88801",
        "timestamp": "2025-03-26T13:45:00.000Z"
    },
    "0141": {
        "value": "16.18043",
        "timestamp": "2025-03-26T13:45:00.000Z"
    },
    "0143": {
        "value": "13.32",
        "timestamp": "2025-03-26T13:45:00.000Z"
    },
    "0144": {
        "value": "18.98604",
        "timestamp": "2025-03-26T13:45:00.000Z"
    },
    "0151": {
        "value": "9.492302",
        "timestamp": "2025-03-26T13:45:00.000Z"
    },
    "0152": {
        "value": "12.96171",
        "timestamp": "2025-03-26T13:45:00.000Z"
    },
    "0153": {
        "value": "7.019214",
        "timestamp": "2025-03-26T13:45:00.000Z"
    },
    "0154": {
        "value": "8.962205",
        "timestamp": "2025-03-26T13:45:00.000Z"
    },
    "0155": {
        "value": "24.08399",
        "timestamp": "2025-03-26T13:40:00.000Z"
    },
    "0161": {
        "value": null,
        "timestamp": "2024-06-16T13:15:00.000Z"
    },
    "0165": {
        "value": null,
        "timestamp": "2024-05-16T16:30:00.000Z"
    },
    "0166": {
        "value": "24.71447",
        "timestamp": "2025-03-26T13:45:00.000Z"
    },
    "0201": {
        "value": "14.78901",
        "timestamp": "2025-03-26T13:45:00.000Z"
    },
    "0202": {
        "value": "22.53283",
        "timestamp": "2025-03-26T13:45:00.000Z"
    },
    "0204": {
        "value": "24.74619",
        "timestamp": "2025-03-26T13:45:00.000Z"
    },
    "0211": {
        "value": "11.38885",
        "timestamp": "2025-03-26T13:45:00.000Z"
    },
    "0212": {
        "value": "22.75989",
        "timestamp": "2025-03-26T13:45:00.000Z"
    },
    "0213": {
        "value": "21.13132",
        "timestamp": "2025-03-26T13:45:00.000Z"
    },
    "0214": {
        "value": "14.52598",
        "timestamp": "2025-03-26T13:45:00.000Z"
    },
    "0221": {
        "value": "13.1869",
        "timestamp": "2025-03-26T13:45:00.000Z"
    },
    "0222": {
        "value": "12.58877",
        "timestamp": "2025-03-26T13:45:00.000Z"
    },
    "0231": {
        "value": "17.59008",
        "timestamp": "2025-03-26T13:45:00.000Z"
    },
    "0241": {
        "value": "19.62301",
        "timestamp": "2025-03-26T13:45:00.000Z"
    },
    "0242": {
        "value": "16.47325",
        "timestamp": "2025-03-26T13:45:00.000Z"
    },
    "0244": {
        "value": "14.58269",
        "timestamp": "2025-03-26T13:40:00.000Z"
    },
    "0245": {
        "value": null,
        "timestamp": "2025-03-17T12:15:00.000Z"
    },
    "0251": {
        "value": "15.21161",
        "timestamp": "2025-03-26T13:45:00.000Z"
    },
    "0252": {
        "value": "19.58508",
        "timestamp": "2025-03-26T13:45:00.000Z"
    },
    "0253": {
        "value": "19.29262",
        "timestamp": "2025-03-26T13:45:00.000Z"
    },
    "0254": {
        "value": "28.55967",
        "timestamp": "2025-03-26T13:45:00.000Z"
    },
    "0255": {
        "value": "15.73397",
        "timestamp": "2025-03-26T13:45:00.000Z"
    },
    "0282": {
        "value": "20.49994",
        "timestamp": "2025-03-26T13:45:00.000Z"
    },
    "0283": {
        "value": "15.05249",
        "timestamp": "2025-03-26T13:45:00.000Z"
    },
    "0288": {
        "value": null,
        "timestamp": "2025-02-20T10:00:00.000Z"
    },
    "0411": {
        "value": "23.75786",
        "timestamp": "2025-03-26T13:45:00.000Z"
    },
    "0412": {
        "value": "21.86712",
        "timestamp": "2025-03-26T13:45:00.000Z"
    },
    "0431": {
        "value": "25.73974",
        "timestamp": "2025-03-26T13:45:00.000Z"
    },
    "0501": {
        "value": "22.80792",
        "timestamp": "2025-03-26T13:40:00.000Z"
    },
    "0502": {
        "value": "22.80197",
        "timestamp": "2025-03-26T13:45:00.000Z"
    },
    "0506": {
        "value": "19.90886",
        "timestamp": "2025-03-26T13:45:00.000Z"
    },
    "0521": {
        "value": "15.86446",
        "timestamp": "2025-03-26T13:45:00.000Z"
    },
    "0531": {
        "value": "27.38342",
        "timestamp": "2025-03-26T13:45:00.000Z"
    },
    "0541": {
        "value": "24.40844",
        "timestamp": "2025-03-26T13:45:00.000Z"
    },
    "0551": {
        "value": "24.72243",
        "timestamp": "2025-03-26T13:40:00.000Z"
    },
    "0601": {
        "value": "23.93932",
        "timestamp": "2025-03-26T13:45:00.000Z"
    },
    "0602": {
        "value": "23.57014",
        "timestamp": "2025-03-26T13:45:00.000Z"
    },
    "0603": {
        "value": "22.06328",
        "timestamp": "2025-03-26T13:45:00.000Z"
    },
    "0621": {
        "value": "24.69583",
        "timestamp": "2025-03-26T13:45:00.000Z"
    },
    "0641": {
        "value": "22.01518",
        "timestamp": "2025-03-26T13:45:00.000Z"
    }
}